pdm_autoexport/__init__.py
pdm_autoexport/hook.py
pdm_autoexport-0.1.1.dist-info/entry_points.txt
pdm_autoexport-0.1.1.dist-info/WHEEL
pdm_autoexport-0.1.1.dist-info/METADATA
pdm_autoexport-0.1.1.dist-info/license_files/LICENSE
pdm_autoexport-0.1.1.dist-info/RECORD
