Metadata-Version: 2.1
Name: pdm-autoexport
Version: 0.1.1
Summary: A PDM plugin to sync the exported files with the project file
License: MIT
Keywords: pdm,plugin
Author-email: Frost Ming <mianghong@gmail.com>
Requires-Python: >=3.7
Classifier: Programming Language :: Python :: 3
Classifier: Programming Language :: Python :: 3 :: Only
Classifier: Programming Language :: Python :: 3.10
Classifier: Programming Language :: Python :: 3.7
Classifier: Programming Language :: Python :: 3.8
Classifier: Programming Language :: Python :: 3.9
Project-URL: Changelog, https://github.com/frostming/pdm-autoexport/releases
Project-URL: Homepage, https://github.com/frostming/pdm-autoexport
